{
  "subject_name": "Software Modeling And Architecture Ele II",
  "subject_slug": "software-modeling-and-architecture-ele-ii-aids",
  "branch": "aids",
  "semester": "sem-6",
  "papers": [
    {
      "pdf_id": "d7ace1e4803d",
      "pdf_url": "https://sppucodes.albatrossc.workers.dev/aids/sem-6/software-modeling-and-architecture-ele-ii-aids/endsem-may-jun-2023-pat2019-smaaeiia.pdf",
      "metadata": {
        "paper_title": "SOFTWARE MODELING AND ARCHITECTURES",
        "academic_year": "T.E.",
        "branch_name": "Computer Engineering/A.I.D.S.",
        "paper_number": "[6003]-360",
        "pattern_year": 2019,
        "semester": "II",
        "subject_code": "310254 D",
        "max_marks": 70,
        "total_questions": 8,
        "duration": "2½ Hours",
        "paper_identifier": "P281",
        "watermark_text": [
          "CEGP013091",
          "49.248.216.238 30/06/2023 10:48:50 static-238"
        ]
      },
      "questions": [
        {
          "question_number": "Q1",
          "subquestion": "a",
          "question_text": "What are the major components of interaction overview diagrams?",
          "marks": 6,
          "question_id": "d7ace1e4803d_q1_a"
        },
        {
          "question_number": "Q1",
          "subquestion": "b",
          "question_text": "What is the types of a state machine diagram? Explain its types in detail.",
          "marks": 6,
          "question_id": "d7ace1e4803d_q1_b"
        },
        {
          "question_number": "Q1",
          "subquestion": "c",
          "question_text": "Explain Fork and Join concept in Activity diagram with a suitable example",
          "marks": 6,
          "question_id": "d7ace1e4803d_q1_c"
        },
        {
          "question_number": "Q2",
          "subquestion": "a",
          "question_text": "Explain the significance of timing diagram with a suitable example.",
          "marks": 6,
          "question_id": "d7ace1e4803d_q2_a"
        },
        {
          "question_number": "Q2",
          "subquestion": "b",
          "question_text": "Draw state machine diagram for coffee vending machine.",
          "marks": 6,
          "question_id": "d7ace1e4803d_q2_b"
        },
        {
          "question_number": "Q2",
          "subquestion": "c",
          "question_text": "Explain Communication diagram with example.",
          "marks": 6,
          "question_id": "d7ace1e4803d_q2_c"
        },
        {
          "question_number": "Q3",
          "subquestion": "a",
          "question_text": "Explain the real time software architecture with a suitable example.",
          "marks": 8,
          "question_id": "d7ace1e4803d_q3_a"
        },
        {
          "question_number": "Q3",
          "subquestion": "b",
          "question_text": "Explain the importance of Object oriented software architecture and its applicabililty in software development?",
          "marks": 9,
          "question_id": "d7ace1e4803d_q3_b"
        },
        {
          "question_number": "Q4",
          "subquestion": "a",
          "question_text": "What is architecture pattern? What is significance of architecting software product?",
          "marks": 5,
          "question_id": "d7ace1e4803d_q4_a"
        },
        {
          "question_number": "Q4",
          "subquestion": "b",
          "question_text": "What is the software architecture? What are the three different views of an architecture? Explain the component of 4+1 architectural view model.",
          "marks": 12,
          "question_id": "d7ace1e4803d_q4_b"
        },
        {
          "question_number": "Q5",
          "subquestion": "a",
          "question_text": "Define the importance of architecture structure and views.",
          "marks": 6,
          "question_id": "d7ace1e4803d_q5_a"
        },
        {
          "question_number": "Q5",
          "subquestion": "b",
          "question_text": "Explain the importance of Object oriented software architecture and its applicability in software development.",
          "marks": 6,
          "question_id": "d7ace1e4803d_q5_b"
        },
        {
          "question_number": "Q5",
          "subquestion": "c",
          "question_text": "Explain the broker pattern for design of service oriented architecture.",
          "marks": 6,
          "question_id": "d7ace1e4803d_q5_c"
        },
        {
          "question_number": "Q6",
          "subquestion": "a",
          "question_text": "Explain the real time software architecture with a suitable example.",
          "marks": 6,
          "question_id": "d7ace1e4803d_q6_a"
        },
        {
          "question_number": "Q6",
          "subquestion": "b",
          "question_text": "Explain synchronous communication pattern in Client server architecture with example?",
          "marks": 6,
          "question_id": "d7ace1e4803d_q6_b"
        },
        {
          "question_number": "Q6",
          "subquestion": "c",
          "question_text": "Explain Location & Platform transparency in service oriented architecture",
          "marks": 6,
          "question_id": "d7ace1e4803d_q6_c"
        },
        {
          "question_number": "Q7",
          "subquestion": "a",
          "question_text": "What is singleton pattern? Explain one example scenario where you will singleton pattern to get applied?",
          "marks": 7,
          "question_id": "d7ace1e4803d_q7_a"
        },
        {
          "question_number": "Q7",
          "subquestion": "b",
          "question_text": "Draw the structure of observer pattern with suitable class diagram including subject and observer.",
          "marks": 6,
          "question_id": "d7ace1e4803d_q7_b"
        },
        {
          "question_number": "Q7",
          "subquestion": "c",
          "question_text": "Explain the broker pattern for design of service oriented architecture",
          "marks": 4,
          "question_id": "d7ace1e4803d_q7_c"
        },
        {
          "question_number": "Q8",
          "subquestion": "a",
          "question_text": "What is Behavioral Pattern? In which situation you use the Behavioral pattern? What is observer Behavioral pattern? Explain observer Behavioral in detail with the applicability of singleton creational pattern.",
          "marks": 9,
          "question_id": "d7ace1e4803d_q8_a"
        },
        {
          "question_number": "Q8",
          "subquestion": "b",
          "question_text": "What are the different approaches of design patterns in software architecture?",
          "marks": 8,
          "question_id": "d7ace1e4803d_q8_b"
        }
      ],
      "extraction_info": {
        "method": "pymupdf_text",
        "used_ocr": false,
        "page_count": 2,
        "character_count": 2853,
        "processed_at": "2026-05-09 12:35:27"
      }
    }
  ]
}
